setup.py
LogrusFormatter.egg-info/PKG-INFO
LogrusFormatter.egg-info/SOURCES.txt
LogrusFormatter.egg-info/dependency_links.txt
LogrusFormatter.egg-info/requires.txt
LogrusFormatter.egg-info/top_level.txt
logrusformatter/__init__.py