Metadata-Version: 1.1
Name: LogrusFormatter
Version: 0.1a0
Summary: The format of the log library for simulating Logrus golang library.
Home-page: https://github.com/velp/logrus-formatter
Author: Vadim Ponomarev
Author-email: velizarx@gmail.com
License: MIT
Platform: UNKNOWN
Classifier: Development Status :: 3 - Alpha
Classifier: Intended Audience :: Developers
Classifier: Environment :: Plugins
Classifier: License :: OSI Approved :: MIT License
Classifier: Operating System :: Unix
Classifier: Operating System :: MacOS
Classifier: Programming Language :: Python :: 2
Classifier: Programming Language :: Python :: 3
Classifier: Topic :: System :: Logging
Classifier: Topic :: Software Development :: Libraries :: Python Modules
